pyexotel/__init__.py
pyexotel/pyexotel.py
pyexotel-1.0.3.dist-info/LICENSE
pyexotel-1.0.3.dist-info/METADATA
pyexotel-1.0.3.dist-info/WHEEL
pyexotel-1.0.3.dist-info/top_level.txt
pyexotel-1.0.3.dist-info/RECORD
