Metadata-Version: 2.1
Name: pyexotel
Version: 1.0.3
Summary: Unofficial Exotel SDK For Python
Author: Bijay Nayak
Author-email: <bijay6779@gmail.com>
Keywords: exotel,exotel api,exotel sdk,pyexotel
Classifier: Development Status :: 5 - Production/Stable
Classifier: Intended Audience :: Developers
Classifier: Programming Language :: Python :: 3
Classifier: Operating System :: Unix
Classifier: Operating System :: MacOS :: MacOS X
Classifier: Operating System :: Microsoft :: Windows
License-File: LICENSE
Requires-Dist: requests
